{
  "contentTypes": [
    {
      "sys": {
        "space": {
          "sys": {
            "type": "Link",
            "linkType": "Space",
            "id": "xurhno9b5wnr"
          }
        },
        "id": "image",
        "type": "ContentType",
        "createdAt": "2023-07-16T19:27:17.275Z",
        "updatedAt": "2023-07-16T19:27:40.372Z",
        "environment": {
          "sys": {
            "id": "master",
            "type": "Link",
            "linkType": "Environment"
          }
        },
        "publishedVersion": 3,
        "publishedAt": "2023-07-16T19:27:40.372Z",
        "firstPublishedAt": "2023-07-16T19:27:17.551Z",
        "createdBy": {
          "sys": {
            "type": "Link",
            "linkType": "User",
            "id": "31q5GvvjY0rWuv9kHbXL5b"
          }
        },
        "updatedBy": {
          "sys": {
            "type": "Link",
            "linkType": "User",
            "id": "31q5GvvjY0rWuv9kHbXL5b"
          }
        },
        "publishedCounter": 2,
        "version": 4,
        "publishedBy": {
          "sys": {
            "type": "Link",
            "linkType": "User",
            "id": "31q5GvvjY0rWuv9kHbXL5b"
          }
        }
      },
      "displayField": "caption",
      "name": "Image",
      "description": "An image/caption for the site",
      "fields": [
        {
          "id": "image",
          "name": "Image",
          "type": "Link",
          "localized": false,
          "required": true,
          "validations": [
            {
              "linkMimetypeGroup": [
                "image"
              ],
              "message": "Please provide an image"
            }
          ],
          "disabled": false,
          "omitted": false,
          "linkType": "Asset"
        },
        {
          "id": "caption",
          "name": "Caption",
          "type": "Symbol",
          "localized": false,
          "required": false,
          "validations": [
          ],
          "disabled": false,
          "omitted": false
        }
      ]
    }
  ],
  "tags": [
  ],
  "editorInterfaces": [
    {
      "sys": {
        "id": "default",
        "type": "EditorInterface",
        "space": {
          "sys": {
            "id": "xurhno9b5wnr",
            "type": "Link",
            "linkType": "Space"
          }
        },
        "version": 4,
        "createdAt": "2023-07-16T19:27:17.639Z",
        "createdBy": {
          "sys": {
            "id": "31q5GvvjY0rWuv9kHbXL5b",
            "type": "Link",
            "linkType": "User"
          }
        },
        "updatedAt": "2023-07-16T19:27:40.900Z",
        "updatedBy": {
          "sys": {
            "id": "31q5GvvjY0rWuv9kHbXL5b",
            "type": "Link",
            "linkType": "User"
          }
        },
        "contentType": {
          "sys": {
            "id": "image",
            "type": "Link",
            "linkType": "ContentType"
          }
        },
        "environment": {
          "sys": {
            "id": "master",
            "type": "Link",
            "linkType": "Environment"
          }
        }
      },
      "controls": [
        {
          "fieldId": "image",
          "widgetId": "assetLinkEditor",
          "widgetNamespace": "builtin"
        },
        {
          "fieldId": "caption",
          "widgetId": "singleLine",
          "widgetNamespace": "builtin"
        }
      ]
    }
  ],
  "entries": [
    {
      "metadata": {
        "tags": [
        ]
      },
      "sys": {
        "space": {
          "sys": {
            "type": "Link",
            "linkType": "Space",
            "id": "xurhno9b5wnr"
          }
        },
        "id": "1bNOGOauvwtlvVArqUwmRq",
        "type": "Entry",
        "createdAt": "2023-07-16T19:31:05.945Z",
        "updatedAt": "2023-07-16T19:35:24.392Z",
        "environment": {
          "sys": {
            "id": "master",
            "type": "Link",
            "linkType": "Environment"
          }
        },
        "publishedVersion": 2,
        "publishedAt": "2023-07-16T19:35:24.392Z",
        "firstPublishedAt": "2023-07-16T19:35:24.392Z",
        "createdBy": {
          "sys": {
            "type": "Link",
            "linkType": "User",
            "id": "31q5GvvjY0rWuv9kHbXL5b"
          }
        },
        "updatedBy": {
          "sys": {
            "type": "Link",
            "linkType": "User",
            "id": "31q5GvvjY0rWuv9kHbXL5b"
          }
        },
        "publishedCounter": 1,
        "version": 3,
        "publishedBy": {
          "sys": {
            "type": "Link",
            "linkType": "User",
            "id": "31q5GvvjY0rWuv9kHbXL5b"
          }
        },
        "automationTags": [
        ],
        "contentType": {
          "sys": {
            "type": "Link",
            "linkType": "ContentType",
            "id": "image"
          }
        }
      },
      "fields": {
        "image": {
          "en-US": {
            "sys": {
              "type": "Link",
              "linkType": "Asset",
              "id": "5gWbFXsd3sZPw23nkrHNMb"
            }
          }
        }
      }
    }
  ],
  "assets": [
    {
      "metadata": {
        "tags": [
        ]
      },
      "sys": {
        "space": {
          "sys": {
            "type": "Link",
            "linkType": "Space",
            "id": "xurhno9b5wnr"
          }
        },
        "id": "5gWbFXsd3sZPw23nkrHNMb",
        "type": "Asset",
        "createdAt": "2023-07-16T19:31:14.883Z",
        "updatedAt": "2023-07-16T19:35:04.299Z",
        "environment": {
          "sys": {
            "id": "master",
            "type": "Link",
            "linkType": "Environment"
          }
        },
        "publishedVersion": 8,
        "publishedAt": "2023-07-16T19:35:04.299Z",
        "firstPublishedAt": "2023-07-16T19:35:04.299Z",
        "createdBy": {
          "sys": {
            "type": "Link",
            "linkType": "User",
            "id": "31q5GvvjY0rWuv9kHbXL5b"
          }
        },
        "updatedBy": {
          "sys": {
            "type": "Link",
            "linkType": "User",
            "id": "31q5GvvjY0rWuv9kHbXL5b"
          }
        },
        "publishedCounter": 1,
        "version": 9,
        "publishedBy": {
          "sys": {
            "type": "Link",
            "linkType": "User",
            "id": "31q5GvvjY0rWuv9kHbXL5b"
          }
        }
      },
      "fields": {
        "title": {
          "en-US": "Cervadae"
        },
        "description": {
          "en-US": "A deer skull"
        },
        "file": {
          "en-US": {
            "url": "//images.ctfassets.net/xurhno9b5wnr/5gWbFXsd3sZPw23nkrHNMb/e306d57cc791440a4e979b0e873c16fd/cervadae.jpg",
            "details": {
              "size": 294427,
              "image": {
                "width": 1536,
                "height": 2048
              }
            },
            "fileName": "cervadae.jpg",
            "contentType": "image/jpeg"
          }
        }
      }
    },
    {
      "metadata": {
        "tags": [
        ]
      },
      "sys": {
        "space": {
          "sys": {
            "type": "Link",
            "linkType": "Space",
            "id": "xurhno9b5wnr"
          }
        },
        "id": "2ygha8GRTs19Ht0QKPECnw",
        "type": "Asset",
        "createdAt": "2023-07-16T19:35:48.003Z",
        "updatedAt": "2023-07-16T19:36:32.882Z",
        "environment": {
          "sys": {
            "id": "master",
            "type": "Link",
            "linkType": "Environment"
          }
        },
        "publishedVersion": 6,
        "publishedAt": "2023-07-16T19:36:32.882Z",
        "firstPublishedAt": "2023-07-16T19:36:32.882Z",
        "createdBy": {
          "sys": {
            "type": "Link",
            "linkType": "User",
            "id": "31q5GvvjY0rWuv9kHbXL5b"
          }
        },
        "updatedBy": {
          "sys": {
            "type": "Link",
            "linkType": "User",
            "id": "31q5GvvjY0rWuv9kHbXL5b"
          }
        },
        "publishedCounter": 1,
        "version": 7,
        "publishedBy": {
          "sys": {
            "type": "Link",
            "linkType": "User",
            "id": "31q5GvvjY0rWuv9kHbXL5b"
          }
        }
      },
      "fields": {
        "title": {
          "en-US": "Farts in a Jar"
        },
        "description": {
          "en-US": "A picture I drew of Isiah and me"
        },
        "file": {
          "en-US": {
            "url": "//images.ctfassets.net/xurhno9b5wnr/2ygha8GRTs19Ht0QKPECnw/b7ae21b96e3a7f30205a654c7fcf8496/farts-in-a-jar.jpg",
            "details": {
              "size": 573600,
              "image": {
                "width": 1600,
                "height": 1600
              }
            },
            "fileName": "farts-in-a-jar.jpg",
            "contentType": "image/jpeg"
          }
        }
      }
    }
  ],
  "locales": [
    {
      "name": "English (United States)",
      "code": "en-US",
      "fallbackCode": null,
      "default": true,
      "contentManagementApi": true,
      "contentDeliveryApi": true,
      "optional": false,
      "sys": {
        "type": "Locale",
        "id": "35QxfmNN9OhPiUTqkHk00u",
        "version": 1,
        "space": {
          "sys": {
            "type": "Link",
            "linkType": "Space",
            "id": "xurhno9b5wnr"
          }
        },
        "environment": {
          "sys": {
            "type": "Link",
            "linkType": "Environment",
            "id": "master",
            "uuid": "81f8fb0e-1fb5-4b42-bdc3-f5fc8cbc7809"
          }
        },
        "createdBy": {
          "sys": {
            "type": "Link",
            "linkType": "User",
            "id": "31q5GvvjY0rWuv9kHbXL5b"
          }
        },
        "createdAt": "2023-07-16T19:25:07Z",
        "updatedBy": {
          "sys": {
            "type": "Link",
            "linkType": "User",
            "id": "31q5GvvjY0rWuv9kHbXL5b"
          }
        },
        "updatedAt": "2023-07-16T19:25:07Z"
      }
    }
  ],
  "webhooks": [
    {
      "name": "Netlify - Deploy a site",
      "url": "https://api.netlify.com/build_hooks/64b44ca2bebe496bb60a89b5",
      "httpBasicUsername": null,
      "topics": [
        "Entry.publish",
        "Asset.publish",
        "Entry.unpublish",
        "Asset.unpublish"
      ],
      "filters": [
        {
          "equals": [
            {
              "doc": "sys.environment.sys.id"
            },
            "master"
          ]
        }
      ],
      "transformation": {
        "contentType": "application/json"
      },
      "active": true,
      "sys": {
        "type": "WebhookDefinition",
        "id": "4Q53BMCT8LmFffuheDZmls",
        "version": 0,
        "space": {
          "sys": {
            "type": "Link",
            "linkType": "Space",
            "id": "xurhno9b5wnr"
          }
        },
        "createdBy": {
          "sys": {
            "type": "Link",
            "linkType": "User",
            "id": "31q5GvvjY0rWuv9kHbXL5b"
          }
        },
        "createdAt": "2023-07-16T20:02:31Z",
        "updatedBy": {
          "sys": {
            "type": "Link",
            "linkType": "User",
            "id": "31q5GvvjY0rWuv9kHbXL5b"
          }
        },
        "updatedAt": "2023-07-16T20:02:31Z"
      },
      "headers": [
      ]
    }
  ],
  "roles": [
    {
      "name": "Author",
      "description": "Allows editing of content",
      "policies": [
        {
          "effect": "allow",
          "actions": [
            "create"
          ],
          "constraint": {
            "and": [
              {
                "equals": [
                  {
                    "doc": "sys.type"
                  },
                  "Entry"
                ]
              }
            ]
          }
        },
        {
          "effect": "allow",
          "actions": [
            "read"
          ],
          "constraint": {
            "and": [
              {
                "equals": [
                  {
                    "doc": "sys.type"
                  },
                  "Entry"
                ]
              }
            ]
          }
        },
        {
          "effect": "allow",
          "actions": [
            "update"
          ],
          "constraint": {
            "and": [
              {
                "equals": [
                  {
                    "doc": "sys.type"
                  },
                  "Entry"
                ]
              }
            ]
          }
        },
        {
          "effect": "allow",
          "actions": [
            "create"
          ],
          "constraint": {
            "and": [
              {
                "equals": [
                  {
                    "doc": "sys.type"
                  },
                  "Asset"
                ]
              }
            ]
          }
        },
        {
          "effect": "allow",
          "actions": [
            "read"
          ],
          "constraint": {
            "and": [
              {
                "equals": [
                  {
                    "doc": "sys.type"
                  },
                  "Asset"
                ]
              }
            ]
          }
        },
        {
          "effect": "allow",
          "actions": [
            "update"
          ],
          "constraint": {
            "and": [
              {
                "equals": [
                  {
                    "doc": "sys.type"
                  },
                  "Asset"
                ]
              }
            ]
          }
        }
      ],
      "permissions": {
        "ContentModel": [
          "read"
        ],
        "Settings": [
        ],
        "ContentDelivery": [
        ],
        "Environments": [
        ],
        "EnvironmentAliases": [
        ],
        "Tags": [
        ]
      },
      "sys": {
        "type": "Role",
        "id": "36ldD1KHFq48UVVt7zItv8",
        "version": 0,
        "space": {
          "sys": {
            "type": "Link",
            "linkType": "Space",
            "id": "xurhno9b5wnr"
          }
        },
        "createdBy": {
          "sys": {
            "type": "Link",
            "linkType": "User",
            "id": "31q5GvvjY0rWuv9kHbXL5b"
          }
        },
        "createdAt": "2023-07-16T19:25:08Z",
        "updatedBy": {
          "sys": {
            "type": "Link",
            "linkType": "User",
            "id": "31q5GvvjY0rWuv9kHbXL5b"
          }
        },
        "updatedAt": "2023-07-16T19:25:08Z"
      }
    },
    {
      "name": "Editor",
      "description": "Allows editing, publishing and archiving of content",
      "policies": [
        {
          "effect": "allow",
          "actions": "all",
          "constraint": {
            "and": [
              {
                "equals": [
                  {
                    "doc": "sys.type"
                  },
                  "Entry"
                ]
              }
            ]
          }
        },
        {
          "effect": "allow",
          "actions": "all",
          "constraint": {
            "and": [
              {
                "equals": [
                  {
                    "doc": "sys.type"
                  },
                  "Asset"
                ]
              }
            ]
          }
        }
      ],
      "permissions": {
        "ContentModel": [
          "read"
        ],
        "Settings": [
        ],
        "ContentDelivery": [
        ],
        "Environments": [
        ],
        "EnvironmentAliases": [
        ],
        "Tags": [
        ]
      },
      "sys": {
        "type": "Role",
        "id": "36lEIYbF7dPNn4GBr6nu2O",
        "version": 0,
        "space": {
          "sys": {
            "type": "Link",
            "linkType": "Space",
            "id": "xurhno9b5wnr"
          }
        },
        "createdBy": {
          "sys": {
            "type": "Link",
            "linkType": "User",
            "id": "31q5GvvjY0rWuv9kHbXL5b"
          }
        },
        "createdAt": "2023-07-16T19:25:08Z",
        "updatedBy": {
          "sys": {
            "type": "Link",
            "linkType": "User",
            "id": "31q5GvvjY0rWuv9kHbXL5b"
          }
        },
        "updatedAt": "2023-07-16T19:25:08Z"
      }
    },
    {
      "name": "Translator",
      "description": "Allows editing of localized fields in the specified language",
      "policies": [
        {
          "effect": "allow",
          "actions": [
            "read"
          ],
          "constraint": {
            "and": [
              {
                "equals": [
                  {
                    "doc": "sys.type"
                  },
                  "Entry"
                ]
              }
            ]
          }
        },
        {
          "effect": "allow",
          "actions": [
            "read"
          ],
          "constraint": {
            "and": [
              {
                "equals": [
                  {
                    "doc": "sys.type"
                  },
                  "Asset"
                ]
              }
            ]
          }
        },
        {
          "effect": "allow",
          "actions": [
            "update"
          ],
          "constraint": {
            "and": [
              {
                "equals": [
                  {
                    "doc": "sys.type"
                  },
                  "Entry"
                ]
              },
              {
                "paths": [
                  {
                    "doc": "fields.%.%"
                  }
                ]
              }
            ]
          }
        },
        {
          "effect": "allow",
          "actions": [
            "update"
          ],
          "constraint": {
            "and": [
              {
                "equals": [
                  {
                    "doc": "sys.type"
                  },
                  "Asset"
                ]
              },
              {
                "paths": [
                  {
                    "doc": "fields.%.%"
                  }
                ]
              }
            ]
          }
        }
      ],
      "permissions": {
        "ContentModel": [
          "read"
        ],
        "Settings": [
        ],
        "ContentDelivery": [
        ],
        "Environments": [
        ],
        "EnvironmentAliases": [
        ],
        "Tags": [
        ]
      },
      "sys": {
        "type": "Role",
        "id": "36m5L3iUQRz2JSDXwdbcnQ",
        "version": 0,
        "space": {
          "sys": {
            "type": "Link",
            "linkType": "Space",
            "id": "xurhno9b5wnr"
          }
        },
        "createdBy": {
          "sys": {
            "type": "Link",
            "linkType": "User",
            "id": "31q5GvvjY0rWuv9kHbXL5b"
          }
        },
        "createdAt": "2023-07-16T19:25:08Z",
        "updatedBy": {
          "sys": {
            "type": "Link",
            "linkType": "User",
            "id": "31q5GvvjY0rWuv9kHbXL5b"
          }
        },
        "updatedAt": "2023-07-16T19:25:08Z"
      }
    }
  ]
}